and_cli/__init__.py
and_cli/commands.py
and_cli-0.4.1.dist-info/entry_points.txt
and_cli-0.4.1.dist-info/WHEEL
and_cli-0.4.1.dist-info/METADATA
and_cli-0.4.1.dist-info/RECORD
