Metadata-Version: 2.1
Name: and-cli
Version: 0.4.1
Summary: Simple CLI for COMP4128
Author: Felix Lonergan
Author-email: felix.lonergan@gmail.com
Requires-Python: >=3.8,<4.0
Classifier: Programming Language :: Python :: 3
Classifier: Programming Language :: Python :: 3.8
Requires-Dist: click (>=7.1.2,<8.0.0)
